{
    "id": "flexibility",
    "cost": 2,
    "name": {
        "en": "Flexibility",
        "de": "Flexibilität"
    },
    "effects": [
        {
            "type": "triggerable",
            "limitType": "PerTurn",
            "limit": 1,
            "action": {
                "trigger": {
                    "type": "addgoal",
                    "goal": "knowhow"
                },
                "effect": {
                    "type": "goal",
                    "goal": "creativity",
                    "amount": 1
                }
            }
        },
        {
            "type": "triggerable",
            "limitType": "PerTurn",
            "limit": 1,
            "action": {
                "trigger": {
                    "type": "addgoal",
                    "goal": "creativity"
                },
                "effect": {
                    "type": "goal",
                    "goal": "knowhow",
                    "amount": 1
                }
            }
        }
    ],
    "image": "Flexibility"
}